CHANGES.rst
CONTRIBUTORS.rst
MANIFEST.in
README.rst
bootstrap-buildout.py
buildout.cfg
setup.py
travis.cfg
docs/LICENSE.GPL
docs/LICENSE.rst
src/collective/__init__.py
src/collective.updatemimetype.egg-info/PKG-INFO
src/collective.updatemimetype.egg-info/SOURCES.txt
src/collective.updatemimetype.egg-info/dependency_links.txt
src/collective.updatemimetype.egg-info/namespace_packages.txt
src/collective.updatemimetype.egg-info/not-zip-safe
src/collective.updatemimetype.egg-info/requires.txt
src/collective.updatemimetype.egg-info/top_level.txt
src/collective/updatemimetype/__init__.py
src/collective/updatemimetype/configure.zcml
src/collective/updatemimetype/interfaces.py
src/collective/updatemimetype/migration.py
src/collective/updatemimetype/setuphandlers.py
src/collective/updatemimetype/testing.py
src/collective/updatemimetype/testing.zcml
src/collective/updatemimetype/browser/__init__.py
src/collective/updatemimetype/browser/configure.zcml
src/collective/updatemimetype/browser/migrate.py
src/collective/updatemimetype/locales/collective.guessmimetype.pot
src/collective/updatemimetype/locales/update.sh
src/collective/updatemimetype/profiles/default/browserlayer.xml
src/collective/updatemimetype/profiles/default/collectiveguessmimetype_marker.txt
src/collective/updatemimetype/profiles/default/metadata.xml
src/collective/updatemimetype/profiles/testing/collectiveguessmimetype_testing.txt
src/collective/updatemimetype/profiles/testing/metadata.xml
src/collective/updatemimetype/tests/__init__.py
src/collective/updatemimetype/tests/test_setup.py