Metadata-Version: 1.1
Name: collective.updatemimetype
Version: 0.1.2
Summary: Plone addon to fix Archetypes file field mimetypes
Home-page: http://pypi.python.org/pypi/collective.updatemimetype
Author: Godefroid Chapelle
Author-email: gotcha@bubblenet.be
License: GPL
Keywords: Python Plone
Platform: UNKNOWN
Classifier: Environment :: Web Environment
Classifier: Framework :: Plone
Classifier: Framework :: Plone :: 4.3
Classifier: Programming Language :: Python
Classifier: Programming Language :: Python :: 2.7
